[
  {
    "name": "james",
    "thought": "Why do you park on a driveway but drive on a parkway?",
    "comments": ["That's legit", "hmmm"]
  },
  {
    "name": "guitarperson",
    "thought": "Nothing is on fire; fire is on things",
    "comments": ["mind blown!"]
  },
  {
    "name": "mayofetish",
    "thought": "Your stomach thinks all potato is mashed",
    "comments": []
  },
  {
    "name": "derkerrjobs",
    "thought": "If I punch myself in the face and it hurts...does that make me weak or strong?",
    "comments": []
  }
]
